LICENSE
VERSION
requirements.txt
pythosf/__init__.py
pythosf/client.py
pythosf/exceptions.py
pythosf/utils.py
pythosf-0.0.9.dist-info/DESCRIPTION.rst
pythosf-0.0.9.dist-info/METADATA
pythosf-0.0.9.dist-info/RECORD
pythosf-0.0.9.dist-info/WHEEL
pythosf-0.0.9.dist-info/metadata.json
pythosf-0.0.9.dist-info/top_level.txt
test/__init__.py
test/live_test.py
